move3/core/__init__.py
move3/core/move1.py
move3/core/move3.py
move3/data/Etowah.csv
move3/data/MOVE1_testData.dss
move3/data/MOVE1_testData.feather
move3/data/Suwanee.csv
move3/data/move1_extended_data.feather
move3/examples/Bulletin17c_example.py
move3/test/__init__.py
move3/test/test.py
move3-0.8.0.dist-info/LICENSE
move3-0.8.0.dist-info/METADATA
move3-0.8.0.dist-info/WHEEL
move3-0.8.0.dist-info/RECORD
