Metadata-Version: 2.3
Name: move3
Version: 0.8.0
Summary: MOVE1 and MOVE3 record extension utilities
License: MIT
Author: Daniel Hamill
Author-email: hamill.daniel@gmail.com
Requires-Python: >=3.9,<3.11
Classifier: License :: OSI Approved :: MIT License
Classifier: Programming Language :: Python :: 3
Classifier: Programming Language :: Python :: 3.9
Classifier: Programming Language :: Python :: 3.10
Requires-Dist: numpy (==1.23.4)
